odoo/addons/sale_loyalty_initial_date_validity/README.rst
odoo/addons/sale_loyalty_initial_date_validity/__init__.py
odoo/addons/sale_loyalty_initial_date_validity/__manifest__.py
odoo/addons/sale_loyalty_initial_date_validity/i18n/it.po
odoo/addons/sale_loyalty_initial_date_validity/i18n/sale_loyalty_initial_date_validity.pot
odoo/addons/sale_loyalty_initial_date_validity/models/__init__.py
odoo/addons/sale_loyalty_initial_date_validity/models/sale_order.py
odoo/addons/sale_loyalty_initial_date_validity/readme/CONTEXT.rst
odoo/addons/sale_loyalty_initial_date_validity/readme/CONTRIBUTORS.rst
odoo/addons/sale_loyalty_initial_date_validity/readme/DESCRIPTION.rst
odoo/addons/sale_loyalty_initial_date_validity/readme/ROADMAP.rst
odoo/addons/sale_loyalty_initial_date_validity/readme/USAGE.rst
odoo/addons/sale_loyalty_initial_date_validity/static/description/icon.png
odoo/addons/sale_loyalty_initial_date_validity/static/description/index.html
odoo/addons/sale_loyalty_initial_date_validity/tests/__init__.py
odoo/addons/sale_loyalty_initial_date_validity/tests/test_sale_loyalty_initial_date_validity.py
odoo_addon_sale_loyalty_initial_date_validity-16.0.1.0.1.dist-info/METADATA
odoo_addon_sale_loyalty_initial_date_validity-16.0.1.0.1.dist-info/WHEEL
odoo_addon_sale_loyalty_initial_date_validity-16.0.1.0.1.dist-info/top_level.txt
odoo_addon_sale_loyalty_initial_date_validity-16.0.1.0.1.dist-info/RECORD
